kick_dl/__init__.py
kick_dl/kick_dl.py
kick_dl-0.1.0.dist-info/METADATA
kick_dl-0.1.0.dist-info/WHEEL
kick_dl-0.1.0.dist-info/entry_points.txt
kick_dl-0.1.0.dist-info/RECORD
