Metadata-Version: 2.1
Name: kick-dl
Version: 0.1.0
Summary: A Python package for fetching and downloading VoDs from Kick channels. Includes support for selecting specific VoDs, listing available streams, and downloading in custom quality with optional concurrency.
License: MIT
Author: Alyetama
Author-email: malyetama@pm.me
Requires-Python: >=3.7,<4.0
Classifier: License :: OSI Approved :: MIT License
Classifier: Programming Language :: Python :: 3
Classifier: Programming Language :: Python :: 3.7
Classifier: Programming Language :: Python :: 3.8
Classifier: Programming Language :: Python :: 3.9
Classifier: Programming Language :: Python :: 3.10
Classifier: Programming Language :: Python :: 3.11
Classifier: Programming Language :: Python :: 3.12
Requires-Dist: cloudscraper (>=1.2.71,<2.0.0)
Requires-Dist: yt_dlp (>=2024.5.27,<2025.0.0)
